twitter_langchain/__init__.py
twitter_langchain/twitter_api_wrapper.py
twitter_langchain/twitter_tool.py
twitter_langchain/twitter_toolkit.py
twitter_langchain-0.0.10.dist-info/METADATA
twitter_langchain-0.0.10.dist-info/WHEEL
twitter_langchain-0.0.10.dist-info/RECORD
