Metadata-Version: 2.3
Name: twitter-langchain
Version: 0.0.10
Summary: Twitter Langchain Toolkit
License: Apache-2.0
Author: John Peterson
Author-email: john.peterson@coinbase.com
Requires-Python: >=3.10,<4.0
Classifier: License :: OSI Approved :: Apache Software License
Classifier: Programming Language :: Python :: 3
Classifier: Programming Language :: Python :: 3.10
Classifier: Programming Language :: Python :: 3.11
Classifier: Programming Language :: Python :: 3.12
Classifier: Programming Language :: Python :: 3.13
Requires-Dist: cdp-agentkit-core (>=0.0.10,<0.0.11)
Requires-Dist: langchain (>=0.3.7,<0.4.0)
Requires-Dist: pydantic (>=2.9.2,<3.0.0)
Requires-Dist: standard-imghdr (>=3.13.0,<4.0.0)
Requires-Dist: tweepy (>=4.14.0,<5.0.0)
